yamlcfg
