Metadata-Version: 1.1
Name: yamlcfg
Version: 0.3.2
Summary: Hierarchical configuration parser
Home-page: https://github.com/RiskIQ/pyyamlcfg
Author: Johan Nestaas
Author-email: johan@riskiq.net
License: BSDv2
Keywords: config,configuration,cfg,yaml,yml
Platform: UNKNOWN
Classifier: Development Status :: 3 - Alpha
Classifier: License :: OSI Approved :: BSD License
Classifier: Environment :: Console
Classifier: Environment :: X11 Applications :: Qt
Classifier: Environment :: MacOS X
Classifier: Environment :: Win32 (MS Windows)
Classifier: Operating System :: POSIX
Classifier: Operating System :: MacOS :: MacOS X
Classifier: Operating System :: Microsoft :: Windows
Classifier: Programming Language :: Python
